{
  "slug": "20260709-1783559412987",
  "title": "ベネズエラ地震、死者3811人に。政府が凍結資金の解除を要求",
  "content": "<h2>ベネズエラ地震と国家危機：投資家が知っておくべき国情報リスク</h2>\n\n<p>最近のニュースで、新興国の経済情報をどこまで投資判断に反映させるべきか、悩んでいる方も多いのではないでしょうか。特にベネズエラのような政治的・経済的混乱が続く国への投資判断は、初心者にとって難しいテーマです。今回のベネズエラ地震による死者数の増加と、政府による海外資金の凍結解除要求というニュースから、私たちが学べる投資の重要なポイントをお伝えします。</p>\n\n<h2>新興国投資のリスク管理：知っておくべき2つのポイント</h2>\n\n<p>結論から言うと、新興国への投資を検討する際は「政治的安定性」と「通貨安定性」の2つを必ずチェックする必要があります。</p>\n\n<p>ベネズエラの事例は、自然災害と国家的な経済危機が同時発生した時、いかに国民の資産が大きな打撃を受けるかを示しています。凍結された海外資金の解除を政府が求めるという状況は、その国の経済が深刻な状態にあることの表れです。例えば、毎月5万円をベネズエラ関連のファンドに積み立てていた投資家も、通貨下落や政治的な予測不可能性によって、元本割れのリスクに直面する可能性があります。</p>\n\n<p>だからこそ、ポートフォリオを組む時は「先進国60%、新興国30%、現金10%」というように、地域や国のリスク分散が重要なのです。特に初心者の方が新興国に投資する場合は、個別国投資ではなく、新興国全体に分散投資するファンドを選ぶことをお勧めします。</p>\n\n<h2>今だからこそ見直す、あなたの投資ポートフォリオ</h2>\n\n<p>ただし新興国投資に対して過度に恐れる必要はありません。長期的には新興国経済の成長性は高く、適切にリスク管理できれば良好なリターンが期待できます。大事なのは、一つの国や地域に偏らないこと、そして定期的に自分のポートフォリオを見直すことです。</p>\n\n<p>難しく考えすぎなくて大丈夫です。まずは日本の証券会社で取り扱う新興国インデックスファンドの説明書を読んでみるところから始めてみましょう。投資知識は経験の積み重ねで自然と身についていきます。</p>\n\n<p><a href=\"https://www.investing.com/news/world-news/death-toll-from-venezuela-quakes-rises-to-3811-4782825\" target=\"_blank\">参照元：Investing.com - Death toll from Venezuela quakes rises to 3,811</a></p>",
  "imageUrl": "https://i-invdn-com.investing.com/trkd-images/LYNXMPEM671IL_L.jpg",
  "source": "Investing.com",
  "sourceUrl": "https://www.investing.com/news/world-news/death-toll-from-venezuela-quakes-rises-to-3811-4782825",
  "publishedAt": "2026-07-09T01:10:12.987Z",
  "tags": [
    "NISA",
    "投資",
    "Investing.com"
  ]
}