{
  "slug": "20260430-1777523846579",
  "title": "NISAで資産を増やす！初心者が知るべき投資の基本",
  "content": "<h1 style=\"font-size:1.8em;color:#2c3e50;margin-bottom:20px;\">政治の一挙手一投足から学ぶ、資産形成における「戦略的判断」の重要性</h1>\n\n<p style=\"font-size:1.05em;line-height:1.8;color:#34495e;\">政界の動きや人間関係の細かな変化に一喜一憂し、その影響が自分の投資判断にまで及ばないか、不安で悩んでいる方も多いのではないでしょうか。実は、政治経済のニュースと私たちの資産運用は、思わぬところで繋がっています。今回は、自民党の麻生太郎副総裁と高市首相の関係悪化説から見えてくる、<span style=\"color:#c0392b;font-weight:bold;\">長期的な資産形成における「本質的な判断」の大切さ</span>についてお話しします。</p>\n\n<h2 style=\"font-size:1.5em;color:#2c3e50;margin-top:30px;border-bottom:3px solid #27ae60;padding-bottom:10px;\">結論：ニュースに左右されない投資姿勢が成功の鍵</h2>\n\n<p style=\"line-height:1.8;color:#34495e;\">東洋経済のニュースが報じた麻生副総裁の動向は、一見すると政治のゴシップに見えるかもしれません。しかし、これは<span style=\"color:#c0392b;font-weight:bold;\">「短期的な人間関係の変化よりも、長期的な立場維持を重視する戦略的思考」</span>を示す好事例です。同様に、私たちの資産運用においても、日々のニュースや市場の小さな変動に心を揺さぶられるのではなく、<span style=\"color:#c0392b;font-weight:bold;\">自分たちの人生設計という「大きなビジョン」に基づいた判断</span>が必要なのです。</p>\n\n<h3 style=\"color:#27ae60;font-size:1.2em;margin-top:25px;\">大事なポイントは3つです</h3>\n\n<ol style=\"line-height:2;color:#34495e;font-size:1.05em;\">\n  <li><span style=\"color:#c0392b;font-weight:bold;\">短期的なニュースに翻弄されない心構え</span>が、長期投資の第一歩</li>\n  <li><span style=\"color:#c0392b;font-weight:bold;\">「焼き魚定食」のような些細な変化より、根本的な方針</span>こそが重要</li>\n  <li>NISA制度を活用した<span style=\"color:#27ae60;font-weight:bold;\">継続的な積み立て</span>こそが、政治変動に左右されない資産を作る</li>\n</ol>\n\n<h2 style=\"font-size:1.5em;color:#2c3e50;margin-top:30px;border-bottom:3px solid #27ae60;padding-bottom:10px;\">長期投資とNISA：戦略的な資産運用の実践</h2>\n\n<p style=\"line-height:1.8;color:#34495e;\">政治の世界が「今この瞬間の関係維持」に注力するように、投資家も短期的な値動きに一喜一憂しがちです。しかし、NISA（少額投資非課税制度）を活用した積立投資は、<span style=\"color:#c0392b;font-weight:bold;\">政治家が長期的なポジション維持を考えるのと同じ戦略</span>なのです。</p>\n\n<p style=\"line-height:1.8;color:#34495e;\">例えば、毎月<span style=\"color:#27ae60;font-weight:bold;\">3万円</span>をつみたてNISAで投資信託に積み立てるとしましょう。</p>\n\n<table style=\"width:100%;margin:20px 0;border-collapse:collapse;font-size:0.95em;\">\n  <tr style=\"background:#27ae60;color:#fff;font-weight:bold;\">\n    <th style=\"padding:12px;border:1px solid #bdc3c7;\">積立期間</th>\n    <th style=\"padding:12px;border:1px solid #bdc3c7;\">年間投資額</th>\n    <th style=\"padding:12px;border:1px solid #bdc3c7;\">累計投資額</th>\n    <th style=\"padding:12px;border:1px solid #bdc3c7;\">年平均3%成長時の資産額（参考値）</th>\n  </tr>\n  <tr style=\"background:#ecf0f1;\">\n    <td style=\"padding:12px;border:1px solid #bdc3c7;\">5年</td>\n    <td style=\"padding:12px;border:1px solid #bdc3c7;\"><span style=\"color:#27ae60;font-weight:bold;\">36万円</span></td>\n    <td style=\"padding:12px;border:1px solid #bdc3c7;\"><span style=\"color:#27ae60;font-weight:bold;\">180万円</span></td>\n    <td style=\"padding:12px;border:1px solid #bdc3c7;\"><span style=\"color:#27ae60;font-weight:bold;\">約188万円</span></td>\n  </tr>\n  <tr>\n    <td style=\"padding:12px;border:1px solid #bdc3c7;\">10年</td>\n    <td style=\"padding:12px;border:1px solid #bdc3c7;\"><span style=\"color:#27ae60;font-weight:bold;\">72万円</span></td>\n    <td style=\"padding:12px;border:1px solid #bdc3c7;\"><span style=\"color:#27ae60;font-weight:bold;\">360万円</span></td>\n    <td style=\"padding:12px;border:1px solid #bdc3c7;\"><span style=\"color:#27ae60;font-weight:bold;\">約398万円</span></td>\n  </tr>\n  <tr style=\"background:#ecf0f1;\">\n    <td style=\"padding:12px;border:1px solid #bdc3c7;\">20年</td>\n    <td style=\"padding:12px;border:1px solid #bdc3c7;\"><span style=\"color:#27ae60;font-weight:bold;\">144万円</span></td>\n    <td style=\"padding:12px;border:1px solid #bdc3c7;\"><span style=\"color:#27ae60;font-weight:bold;\">720万円</span></td>\n    <td style=\"padding:12px;border:1px solid #bdc3c7;\"><span style=\"color:#27ae60;font-weight:bold;\">約900万円</span></td>\n  </tr>\n</table>\n\n<p style=\"line-height:1.8;color:#34495e;\">このように、<span style=\"color:#27ae60;font-weight:bold;\">20年の継続投資</span>により、投資額<span style=\"color:#27ae60;font-weight:bold;\">720万円</span>が<span style=\"color:#27ae60;font-weight:bold;\">約900万円</span>へと成長する可能性があります。これこそが、政治の短期的な変動よりも大切な、<span style=\"color:#c0392b;font-weight:bold;\">「時間を味方にする投資戦略」</span>なのです。</p>\n\n<div style=\"background:#e8f8f5;border-left:4px solid #27ae60;padding:14px 18px;margin:20px 0;border-radius:6px;\">\n  <p style=\"margin:0;color:#27ae60;font-weight:bold;\">✓ ポイント</p>\n  <p style=\"margin:8px 0 0 0;color:#34495e;\">NISA制度の非課税メリットと、継続的な積立の力を組み合わせることで、政治変動や市場の一時的な混乱に左右されない、堅実な資産形成が可能になります。</p>\n</div>\n\n<div style=\"background:#fff8e1;border-left:4px solid #f39c12;padding:14px 18px;margin:20px 0;border-radius:6px;\">\n  <p style=\"margin:0;color:#e67e22;font-weight:bold;\">⚠️ リスク注意</p>\n  <p style=\"margin:8px 0 0 0;color:#34495e;\">上記シミュレーションは年平均3%の成長を想定したもので、実際の市場環境によっては変動します。また、政治的な大きな変化が経済に与える影響は無視できません。投資は自分のリスク許容度を考慮した上で、無理のない範囲で行うことが大切です。</p>\n</div>\n\n<h2 style=\"font-size:1.5em;color:#2c3e50;margin-top:30px;border-bottom:3px solid",
  "imageUrl": "https://tk.ismcdn.jp/mwimgs/6/8/1200w/img_6811f0d58ac23afc1d07ba8d6a2081ad66512.jpg?nextgen=false",
  "source": "東洋経済マネー",
  "sourceUrl": "https://toyokeizai.net/articles/-/943119?utm_source=rss&utm_medium=http&utm_campaign=link_back",
  "publishedAt": "2026-04-30T04:37:26.579Z",
  "tags": [
    "NISA",
    "投資",
    "東洋経済マネー"
  ]
}