{
  "slug": "20260420-1776658474858",
  "title": "ドル高！中東情勢で相場が動く理由を解説",
  "content": "<h2>中東情勢緊迫がドル高を加速　為替変動で資産運用への影響を考える</h2>\n\n<p>最近、為替相場の変動が大きくなっているというニュースを見かけて、「自分の資産運用に影響があるのでは？」と心配で悩んでいる方も多いのではないでしょうか。先日、中東情勢の緊迫化を受けてドルが1週間ぶりの高値をつけたというニュースが報じられました。こうした国際的な事件や紛争が、実は私たちの投資にどのような影響を与えるのかについて、ファイナンシャルプランナーの視点からご説明したいと思います。</p>\n\n<h2>ドル高が起きる仕組みと投資への影響</h2>\n\n<p>結論から言うと、地政学的なリスク（政治的な危機や紛争）が高まると、投資家は相対的に「安全」とされる資産を求める傾向があります。ドルは国際的な基軸通貨であり、いざという時の避難先として機能することが多いため、こうした局面ではドル買いが進みやすいのです。今回の中東情勢緊迫化についても同じ背景があります。</p>\n\n<p>大事なポイントは2つです。ひとつ目は、為替変動は長期的な資産運用にはそこまで大きな影響を与えないということ。たとえば、毎月3万円を国際分散投資で積み立てていたとしても、1年後には約36万円、10年後には約360万円の資産が形成されます。短期的な為替の上下よりも、継続的な積み立てと時間の力の方がはるかに重要なのです。ふたつ目は、短期的な値動きで一喜一憂しないという姿勢です。市場は常に新しい情報に反応しますが、優れた長期投資家は目先の変動には惑わされません。</p>\n\n<h2>NISA制度を活用した安定運用を心がけましょう</h2>\n\n<p>こうした市場変動の時こそ、NISA（少額投資非課税制度）の活用が有効です。毎月一定額を積み立てるNISAなら、市場の上下を活用して自動的に「安く買って、高く売る」という理想的なタイミングが実現しやすくなります。</p>\n\n<p>ただし為替変動に関しては、特に海外資産への投資では注意が必要です。ドル高が進行すると、ドル建ての資産は円換算では目減りすることもあります。また市場全体の混乱時には、元本割れのリスクもあります。だからこそ、複数の資産クラスに分散投資することが大切なのです。</p>\n\n<p>難しく考えすぎなくて大丈夫です。世界情勢の変化は確かに存在しますが、それでも長期的には経済成長とともに資産は増えていくものです。まずは自分の投資目標と期間を整理して、それに合わせた毎月の積み立てから始めてみましょう。</p>\n\n<p><a href=\"https://www.investing.com/news/forex-news/dollar-rebounds-as-middle-east-tensions-reignite-hormuz-closed-4622264\" target=\"_blank\">参照元：Investing.com「Dollar pushes to one-week high as Middle East tensions reignite」</a></p>",
  "imageUrl": "https://i-invdn-com.investing.com/trkd-images/LYNXMPEM3I0CY_L.jpg",
  "source": "Investing.com",
  "sourceUrl": "https://www.investing.com/news/forex-news/dollar-rebounds-as-middle-east-tensions-reignite-hormuz-closed-4622264",
  "publishedAt": "2026-04-20T04:14:34.858Z",
  "tags": [
    "NISA",
    "投資",
    "Investing.com"
  ]
}